bangshim/__init__.py
bangshim/asset/__init__.py
bangshim/asset/shim.exe
bangshim/bangshim.py
bangshim-0.2.0.dist-info/WHEEL
bangshim-0.2.0.dist-info/entry_points.txt
bangshim-0.2.0.dist-info/METADATA
bangshim-0.2.0.dist-info/RECORD
