Metadata-Version: 2.3
Name: bangshim
Version: 0.2.0
Summary: From sheBanG to Shim
License: 
Classifier: Programming Language :: Python
Classifier: Programming Language :: Python :: 3.11
Classifier: Programming Language :: Python :: 3.12
Classifier: Programming Language :: Python :: 3.13
Classifier: Programming Language :: Python :: Implementation :: CPython
Requires-Python: >=3.13
